vision_v0/__init__.py
vision_v0/envs/__init__.py
vision_v0/envs/vision_env.py
vision_v0-0.9.8.dist-info/METADATA
vision_v0-0.9.8.dist-info/WHEEL
vision_v0-0.9.8.dist-info/top_level.txt
vision_v0-0.9.8.dist-info/RECORD
